cursofiapkalil/__init__.py
cursofiapkalil/core.py
cursofiapkalil_package-1.0.0.dist-info/METADATA
cursofiapkalil_package-1.0.0.dist-info/WHEEL
cursofiapkalil_package-1.0.0.dist-info/top_level.txt
cursofiapkalil_package-1.0.0.dist-info/RECORD
