Metadata-Version: 2.1
Name: cursofiapkalil-package
Version: 1.0.0
Summary: Descricao da sua lib cursofiapkalil
Home-page: https://github.com/tadrianonet/cursofiapkalil
Author: Kali Gadben
Author-email: kalil.gadben@gmail.com
License: MIT
